create_apps_in_chatgpt-1.3.6.dist-info/licenses/LICENSE
fastapps/__init__.py
fastapps/auth/__init__.py
fastapps/auth/decorators.py
fastapps/auth/verifier.py
fastapps/builder/__init__.py
fastapps/builder/build-all.mts
fastapps/builder/compiler.py
fastapps/cli/__init__.py
fastapps/cli/main.py
fastapps/cli/commands/__init__.py
fastapps/cli/commands/build.py
fastapps/cli/commands/create.py
fastapps/cli/commands/dev.py
fastapps/cli/commands/init.py
fastapps/cli/commands/use.py
fastapps/cli/commands/cloud/__init__.py
fastapps/cli/commands/cloud/delete.py
fastapps/cli/commands/cloud/deploy.py
fastapps/cli/commands/cloud/deployments.py
fastapps/cli/commands/cloud/link.py
fastapps/cli/commands/cloud/login.py
fastapps/cli/commands/cloud/logout.py
fastapps/cli/commands/cloud/projects.py
fastapps/cli/commands/cloud/status.py
fastapps/cli/commands/cloud/unlink.py
fastapps/cli/commands/cloud/whoami.py
fastapps/cloud/__init__.py
fastapps/cloud/client.py
fastapps/cloud/config.py
fastapps/cloud/models.py
fastapps/cloud/projects_manager.py
fastapps/core/__init__.py
fastapps/core/server.py
fastapps/core/utils.py
fastapps/core/widget.py
fastapps/deployer/__init__.py
fastapps/deployer/auth.py
fastapps/deployer/client.py
fastapps/deployer/packager.py
fastapps/templates/albums/tool.py
fastapps/templates/albums/widget/AlbumCard.jsx
fastapps/templates/albums/widget/FilmStrip.jsx
fastapps/templates/albums/widget/FullscreenViewer.jsx
fastapps/templates/albums/widget/index.css
fastapps/templates/albums/widget/index.jsx
fastapps/templates/albums/widget/hooks/types.ts
fastapps/templates/albums/widget/hooks/use-max-height.ts
fastapps/templates/albums/widget/hooks/use-openai-global.ts
fastapps/templates/carousel/tool.py
fastapps/templates/carousel/widget/Card.jsx
fastapps/templates/carousel/widget/index.css
fastapps/templates/carousel/widget/index.jsx
fastapps/templates/default/tool.py
fastapps/templates/default/widget/index.jsx
fastapps/templates/list/tool.py
fastapps/templates/list/widget/index.css
fastapps/templates/list/widget/index.jsx
create_apps_in_chatgpt-1.3.6.dist-info/METADATA
create_apps_in_chatgpt-1.3.6.dist-info/WHEEL
create_apps_in_chatgpt-1.3.6.dist-info/entry_points.txt
create_apps_in_chatgpt-1.3.6.dist-info/top_level.txt
create_apps_in_chatgpt-1.3.6.dist-info/RECORD
